health_bsa/__init__.py
health_bsa/bsa.py
health_bsa-0.1.1.dist-info/METADATA
health_bsa-0.1.1.dist-info/WHEEL
health_bsa-0.1.1.dist-info/RECORD
