Metadata-Version: 2.1
Name: health-bsa
Version: 0.1.1
Summary: This is a small tool to compute Body Surface Area of a human body based on height and weight
Home-page: https://github.com/lamnvcnsh/health-bsa/
License: MIT
Keywords: Body Surface Area,Health index
Author: LamNguyen
Author-email: lamnvcnsh@gmail.com
Requires-Python: >=3.8,<4.0
Classifier: License :: OSI Approved :: MIT License
Classifier: Programming Language :: Python :: 3
Classifier: Programming Language :: Python :: 3.8
Classifier: Programming Language :: Python :: 3.9
Classifier: Programming Language :: Python :: 3.10
Classifier: Programming Language :: Python :: 3.11
Project-URL: Repository, https://github.com/lamnvcnsh/health-bsa
